{
  "AdverseEvent": [
    "actuality",
    "category",
    "event",
    "subject",
    "encounter",
    "resultingCondition",
    "suspectEntity.instance"
  ],
  "AllergyIntolerance": [
    "clinicalStatus",
    "verificationStatus",
    "type",
    "category",
    "criticality",
    "code",
    "patient",
    "encounter",
    "recordedDate",
    "reaction",
    "reaction.extension",
    "reaction.manifestation",
    "reaction.onset",
    "reaction.severity"
  ],
  "BodyStructure": [
    "active",
    "location",
    "locationQualifier",
    "patient"
  ],
  "CarePlan": [
    "text",
    "text.status",
    "status",
    "intent",
    "category",
    "subject"
  ],
  "CareTeam": [
    "status",
    "subject",
    "participant",
    "participant.role",
    "participant.member"
  ],
  "Claim": [
    "patient",
    "billablePeriod",
    "created",
    "provider",
    "prescription"
  ],
  "Communication": [
    "status",
    "statusReason",
    "category",
    "medium",
    "subject",
    "encounter",
    "sent",
    "received",
    "recipient",
    "sender",
    "reasonCode",
    "extension",
    "reasonCode.extension"
  ],
  "CommunicationRequest": [
    "status",
    "category",
    "doNotPerform",
    "subject",
    "encounter",
    "recipient",
    "sender"
  ],
  "Condition": [
    "clinicalStatus",
    "verificationStatus",
    "category",
    "severity",
    "code",
    "bodySite",
    "subject",
    "encounter",
    "onset",
    "abatement",
    "recordedDate",
    "stage",
    "stage.summary"
  ],
  "Coverage": [
    "type",
    "policyHolder",
    "beneficiary",
    "period",
    "payor"
  ],
  "Device": [
    "patient"
  ],
  "DeviceRequest": [
    "extension",
    "modifierExtension",
    "modifierExtension.value",
    "status",
    "intent",
    "code",
    "code.extension",
    "subject",
    "encounter",
    "authoredOn",
    "note",
    "identifier",
    "occurrence",
    "requester",
    "performer",
    "reasonReference"
  ],
  "DeviceUseStatement": [
    "status",
    "subject",
    "timing",
    "recordedOn",
    "device",
    "bodySite"
  ],
  "DiagnosticReport": [
    "status",
    "category",
    "code",
    "subject",
    "effective",
    "issued",
    "performer",
    "result",
    "conclusion",
    "conclusionCode",
    "encounter",
    "imagingStudy",
    "presentedForm"
  ],
  "Encounter": [
    "extension",
    "identifier",
    "identifier.system",
    "identifier.value",
    "status",
    "class",
    "type",
    "priority",
    "subject",
    "participant",
    "participant.type",
    "participant.period",
    "participant.individual",
    "period",
    "length",
    "reasonCode",
    "diagnosis",
    "diagnosis.extension",
    "diagnosis.condition",
    "diagnosis.use",
    "diagnosis.rank",
    "hospitalization",
    "hospitalization.admitSource",
    "hospitalization.reAdmission",
    "hospitalization.dischargeDisposition",
    "location",
    "location.location",
    "location.period",
    "serviceProvider"
  ],
  "FamilyMemberHistory": [
    "patient",
    "date",
    "relationship",
    "age",
    "deceased",
    "condition.code"
  ],
  "Flag": [
    "status",
    "category",
    "code",
    "subject",
    "period"
  ],
  "Goal": [
    "lifecycleStatus",
    "achievementStatus",
    "category",
    "description",
    "subject",
    "target",
    "target.due",
    "statusDate",
    "addresses"
  ],
  "ImagingStudy": [
    "subject",
    "started",
    "basedOn",
    "procedureReference"
  ],
  "Immunization": [
    "status",
    "statusReason",
    "vaccineCode",
    "patient",
    "occurrence",
    "recorded",
    "primarySource",
    "vaccineCode.extension"
  ],
  "ImmunizationEvaluation": [
    "identifier",
    "status",
    "patient",
    "date",
    "targetDisease",
    "immunizationEvent",
    "doseStatus",
    "doseStatusReason"
  ],
  "ImmunizationRecommendation": [
    "patient",
    "recommendation",
    "recommendation.vaccineCode",
    "recommendation.doseNumber"
  ],
  "Location": [
    "identifier",
    "identifier.use",
    "identifier.system",
    "identifier.value",
    "status",
    "name",
    "mode",
    "type",
    "telecom",
    "address",
    "address.line",
    "address.city",
    "address.state",
    "address.postalCode",
    "managingOrganization"
  ],
  "Medication": [
    "code"
  ],
  "MedicationAdministration": [
    "status",
    "statusReason",
    "medication",
    "subject",
    "context",
    "effective",
    "reasonCode",
    "dosage.route",
    "dosage.dose",
    "extension",
    "medication.extension"
  ],
  "MedicationDispense": [
    "status",
    "statusReason",
    "medication",
    "subject",
    "quantity",
    "daysSupply",
    "whenPrepared",
    "whenHandedOver",
    "dosageInstruction.timing",
    "dosageInstruction.route",
    "dosageInstruction.doseAndRate",
    "dosageInstruction.doseAndRate.type",
    "dosageInstruction.doseAndRate.dose",
    "extension",
    "medication.extension"
  ],
  "MedicationRequest": [
    "status",
    "intent",
    "category",
    "doNotPerform",
    "reported",
    "medication",
    "subject",
    "encounter",
    "authoredOn",
    "requester",
    "dosageInstruction",
    "dosageInstruction.text",
    "dosageInstruction.timing",
    "dosageInstruction.timing.repeat",
    "dosageInstruction.timing.repeat.frequency",
    "dosageInstruction.timing.repeat.frequencyMax",
    "dosageInstruction.timing.repeat.period",
    "dosageInstruction.timing.repeat.periodMax",
    "dosageInstruction.timing.repeat.periodUnit",
    "dosageInstruction.asNeeded",
    "dosageInstruction.site",
    "dosageInstruction.doseAndRate",
    "dosageInstruction.doseAndRate.dose",
    "dispenseRequest",
    "dispenseRequest.initialFill",
    "dispenseRequest.dispenseInterval",
    "dispenseRequest.validityPeriod",
    "dispenseRequest.numberOfRepeatsAllowed",
    "dispenseRequest.quantity",
    "dispenseRequest.expectedSupplyDuration",
    "medication.extension",
    "reasonCode"
  ],
  "MedicationStatement": [
    "status",
    "medication",
    "subject",
    "effective",
    "dateAsserted",
    "informationSource",
    "derivedFrom",
    "dosage.timing",
    "dosage.route",
    "dosage.doseAndRate",
    "dosage.doseAndRate.dose"
  ],
  "NutritionOrder": [
    "identifier",
    "patient"
  ],
  "Observation": [
    "status",
    "category",
    "code",
    "subject",
    "encounter",
    "effective",
    "issued",
    "value",
    "interpretation",
    "bodySite",
    "method",
    "specimen",
    "component",
    "component.code",
    "component.value",
    "component.dataAbsentReason",
    "component.interpretation",
    "extension",
    "code.extension"
  ],
  "Organization": [
    "identifier",
    "identifier.use",
    "identifier.value",
    "active",
    "type",
    "name",
    "telecom",
    "address",
    "address.line",
    "address.city",
    "address.state",
    "address.postalCode",
    "address.country",
    "endpoint"
  ],
  "Patient": [
    "extension",
    "identifier",
    "identifier.system",
    "identifier.value",
    "name",
    "name.family",
    "name.given",
    "telecom",
    "telecom.system",
    "telecom.value",
    "telecom.use",
    "gender",
    "birthDate",
    "deceased",
    "address",
    "address.line",
    "address.city",
    "address.state",
    "address.postalCode",
    "address.period",
    "communication",
    "communication.language"
  ],
  "Practitioner": [
    "identifier",
    "identifier.use",
    "identifier.value",
    "name",
    "name.family"
  ],
  "PractitionerRole": [
    "identifier",
    "identifier.use",
    "identifier.system",
    "identifier.value",
    "active",
    "period",
    "practitioner",
    "organization",
    "code",
    "specialty",
    "location",
    "telecom",
    "telecom.system",
    "telecom.value",
    "endpoint"
  ],
  "Procedure": [
    "extension",
    "status",
    "code",
    "subject",
    "encounter",
    "performed",
    "performer",
    "reasonCode",
    "bodySite",
    "report",
    "usedCode",
    "statusReason",
    "code.extension",
    "performed.extension"
  ],
  "RelatedPerson": [
    "patient",
    "relationship",
    "gender",
    "period"
  ],
  "ServiceRequest": [
    "extension",
    "modifierExtension",
    "status",
    "doNotPerform",
    "code",
    "code.extension",
    "subject",
    "encounter",
    "occurrence",
    "authoredOn",
    "bodySite",
    "intent",
    "asNeeded",
    "reasonCode"
  ],
  "Specimen": [
    "type",
    "subject",
    "receivedTime",
    "collection.collected",
    "collection.bodySite",
    "processing.procedure"
  ],
  "Substance": [
    "code",
    "instance.quantity",
    "ingredient.quantity",
    "ingredient.substance"
  ],
  "Task": [
    "identifier",
    "status",
    "intent",
    "priority",
    "code",
    "code.extension",
    "executionPeriod"
  ]
}